vendi_sdk/__init__.py
vendi_sdk/completions/__init__.py
vendi_sdk/completions/completions.py
vendi_sdk/completions/schema.py
vendi_sdk/core/__init__.py
vendi_sdk/core/ahttp_client.py
vendi_sdk/core/config.py
vendi_sdk/core/http_client.py
vendi_sdk/core/schema.py
vendi_sdk/datasets/__init__.py
vendi_sdk/datasets/datasets.py
vendi_sdk/datasets/schema.py
vendi_sdk/deployments/__init__.py
vendi_sdk/deployments/deployments.py
vendi_sdk/deployments/schema.py
vendi_sdk/finetune/__init__.py
vendi_sdk/finetune/finetune.py
vendi_sdk/finetune/schema.py
vendi_sdk/models/__init__.py
vendi_sdk/models/models.py
vendi_sdk/models/schema.py
vendi_sdk/runtime/__init__.py
vendi_sdk/runtime/constants.py
vendi_sdk/runtime/decorators.py
vendi_sdk/runtime/instrument.py
vendi_sdk/runtime/runtime.py
vendi_sdk/runtime/span_processer.py
vendi_sdk/vendi.py
vendi_sdk-0.2.3.dist-info/METADATA
vendi_sdk-0.2.3.dist-info/WHEEL
vendi_sdk-0.2.3.dist-info/RECORD
