Metadata-Version: 2.1
Name: vendi-sdk
Version: 0.2.3
Summary: Vendi SDK
Author: Aviv.a
Author-email: aviv@vendi-ai.com
Requires-Python: >=3.10,<4.0
Classifier: Programming Language :: Python :: 3
Classifier: Programming Language :: Python :: 3.10
Classifier: Programming Language :: Python :: 3.11
Classifier: Programming Language :: Python :: 3.12
Requires-Dist: aiohttp (>=3.8.1,<4.0.0)
Requires-Dist: pandas
Requires-Dist: pydantic (>=2.5.2,<3.0.0)
Requires-Dist: pydantic-settings (>=2.1.0,<3.0.0)
Requires-Dist: requests (>=2.31.0,<3.0.0)
Requires-Dist: sentry-sdk (>=2.2.0,<3.0.0)
Requires-Dist: tenacity (>=8.2.3,<9.0.0)
Requires-Dist: traceloop-sdk (>=0.21.4,<0.22.0)
